bmsdna/lakeapi/__init__.py
bmsdna/lakeapi/api/__init__.py
bmsdna/lakeapi/api/api.py
bmsdna/lakeapi/context/__init__.py
bmsdna/lakeapi/context/df_base.py
bmsdna/lakeapi/context/df_duckdb.py
bmsdna/lakeapi/context/df_odbc.py
bmsdna/lakeapi/context/df_polars.py
bmsdna/lakeapi/context/source_uri.py
bmsdna/lakeapi/core/__init__.py
bmsdna/lakeapi/core/config.py
bmsdna/lakeapi/core/datasource.py
bmsdna/lakeapi/core/env.py
bmsdna/lakeapi/core/log.py
bmsdna/lakeapi/core/model.py
bmsdna/lakeapi/core/partition_utils.py
bmsdna/lakeapi/core/response.py
bmsdna/lakeapi/core/route.py
bmsdna/lakeapi/core/schema_cache.py
bmsdna/lakeapi/core/types.py
bmsdna/lakeapi/core/uservalidation.py
bmsdna/lakeapi/core/yaml.py
bmsdna/lakeapi/endpoint/__init__.py
bmsdna/lakeapi/endpoint/detail_endpoint.py
bmsdna/lakeapi/endpoint/endpoint.py
bmsdna/lakeapi/endpoint/endpoint_nearby.py
bmsdna/lakeapi/endpoint/endpoint_search.py
bmsdna/lakeapi/endpoint/sql_endpoint.py
bmsdna/lakeapi/standalone/__init__.py
bmsdna/lakeapi/tools/useradd.py
bmsdna/lakeapi/tools/validateschema.py
bmsdna/lakeapi/utils/async_utils.py
bmsdna/lakeapi/utils/fast_api_utils.py
bmsdna/lakeapi/utils/meta_cache.py
bmsdna_lakeapi-0.27.6.dist-info/METADATA
bmsdna_lakeapi-0.27.6.dist-info/WHEEL
bmsdna_lakeapi-0.27.6.dist-info/entry_points.txt
bmsdna_lakeapi-0.27.6.dist-info/licenses/LICENSE
bmsdna_lakeapi-0.27.6.dist-info/RECORD
